sspaf/__init__.py
sspaf/sspaf_bin.py
sspaf/core/__init__.py
sspaf/core/create.py
sspaf/core/publish.py
sspaf/core/render.py
sspaf/core/serve.py
sspaf/core/assets/__init__.py
sspaf/core/assets/init.py
sspaf/core/assets/js.py
sspaf-0.0.18.dist-info/LICENSE
sspaf-0.0.18.dist-info/METADATA
sspaf-0.0.18.dist-info/WHEEL
sspaf-0.0.18.dist-info/entry_points.txt
sspaf-0.0.18.dist-info/top_level.txt
sspaf-0.0.18.dist-info/RECORD
