Metadata-Version: 2.1
Name: sspaf
Version: 0.0.18
Summary: A superglued single page application framework
Home-page: https://github.com/0xleft/sspaf
Author: plusleft
Author-email: UNKNOWN
License: UNKNOWN
Platform: UNKNOWN
Requires-Dist: flask
Requires-Dist: waitress
